zlib_into.cpython-311-x86_64-linux-gnu.so
zlib_into-0.4.dist-info/METADATA
zlib_into-0.4.dist-info/WHEEL
zlib_into-0.4.dist-info/top_level.txt
zlib_into-0.4.dist-info/RECORD
zlib_into-0.4.dist-info/licenses/LICENSE.md
