Metadata-Version: 2.4
Name: zlib-into
Version: 0.4
Summary: Compress & decompress data with zlib into preallocated buffers
Author-email: European XFEL GmbH <da-support@xfel.eu>
License-Expression: MPL-2.0
Project-URL: Source, https://git.xfel.eu/dataAnalysis/zlib_into
Project-URL: Changelog, https://git.xfel.eu/dataAnalysis/zlib_into/-/blob/main/CHANGES.md
Classifier: Topic :: System :: Archiving :: Compression
Requires-Python: >=3.10
License-File: LICENSE.md
Provides-Extra: test
Requires-Dist: numpy; extra == "test"
Requires-Dist: pytest; extra == "test"
Dynamic: license-file
